pulearn/__init__.py
pulearn/_version.py
pulearn/bagging.py
pulearn/elkanoto.py
pulearn/metrics.py
pulearn/version.info
pulearn-0.0.11.dist-info/LICENSE.md
pulearn-0.0.11.dist-info/LICENSE_NOTICE.md
pulearn-0.0.11.dist-info/METADATA
pulearn-0.0.11.dist-info/WHEEL
pulearn-0.0.11.dist-info/top_level.txt
pulearn-0.0.11.dist-info/RECORD
