Metadata-Version: 2.1
Name: pulearn
Version: 0.0.11
Summary: Positive-unlabeled learning with Python
Author-email: Shay Palachy Affek <shay.palachy@gmail.com>
Project-URL: Source, https://github.com/pulearn/pulearn
Keywords: machine-learning,positive-unlabeled-learning,pulearning
Classifier: Development Status :: 4 - Beta
Classifier: Intended Audience :: Developers
Classifier: License :: OSI Approved :: BSD License
Classifier: Programming Language :: Python
Classifier: Programming Language :: Python :: 3 :: Only
Classifier: Programming Language :: Python :: 3.8
Classifier: Programming Language :: Python :: 3.9
Classifier: Programming Language :: Python :: 3.10
Classifier: Programming Language :: Python :: 3.11
Classifier: Programming Language :: Python :: 3.12
Classifier: Topic :: Other/Nonlisted Topic
Classifier: Topic :: Software Development :: Libraries
Classifier: Topic :: Software Development :: Libraries :: Python Modules
Classifier: Topic :: Utilities
License-File: LICENSE.md
License-File: LICENSE_NOTICE.md
Requires-Dist: numpy~=1.26.4
Requires-Dist: scikit-learn<1.6,>=1.4.2
Requires-Dist: six~=1.16.0
